power_vision_AI_of_the_tiger/AI_tiger_app.py
power_vision_AI_of_the_tiger/__init__.py
power_vision_AI_of_the_tiger/classify_video.py
power_vision_AI_of_the_tiger/evaluate.py
power_vision_AI_of_the_tiger/train.py
power_vision_AI_of_the_tiger/Classifier/__init__.py
power_vision_AI_of_the_tiger/Classifier/classifier.py
power_vision_AI_of_the_tiger/Classifier/metrics.py
power_vision_AI_of_the_tiger/PoseClassification/__init__.py
power_vision_AI_of_the_tiger/PoseClassification/bootstrap.py
power_vision_AI_of_the_tiger/PoseClassification/pose_classifier.py
power_vision_AI_of_the_tiger/PoseClassification/pose_embedding.py
power_vision_AI_of_the_tiger/PoseClassification/utils.py
power_vision_AI_of_the_tiger/PoseClassification/visualize.py
power_vision_AI_of_the_tiger/data/csv_out/fall.csv
power_vision_AI_of_the_tiger/data/csv_out/not_fall.csv
power_vision_AI_of_the_tiger/data/full_csv/poses_csvs_out.csv
power_vision_AI_of_the_tiger/video/__init__.py
power_vision_AI_of_the_tiger/video/video.py
power_vision_ai_of_the_tiger-0.0.21.dist-info/METADATA
power_vision_ai_of_the_tiger-0.0.21.dist-info/WHEEL
power_vision_ai_of_the_tiger-0.0.21.dist-info/entry_points.txt
power_vision_ai_of_the_tiger-0.0.21.dist-info/licenses/LICENSE
power_vision_ai_of_the_tiger-0.0.21.dist-info/RECORD
