Metadata-Version: 2.1
Name: power_vision_AI_of_the_tiger
Version: 0.0.21
Summary: A package to detect falls.
Project-URL: GitHub, https://github.com/aappolaire/power_vision_AI_of_the_tiger
Project-URL: Bug Tracker, https://github.com/aappolaire/power_vision_AI_of_the_tiger/issues
Author: Alexandre A., Aline C., Thibault F.
License-File: LICENSE
Classifier: License :: OSI Approved :: GNU General Public License v2 (GPLv2)
Classifier: Operating System :: POSIX :: Linux
Classifier: Programming Language :: Python :: 3
Requires-Python: >=3.9
Requires-Dist: mediapipe
Requires-Dist: moviepy
Requires-Dist: pandas
Requires-Dist: pillow
Requires-Dist: requests
Requires-Dist: scikit-learn
Requires-Dist: streamlit-webrtc
Requires-Dist: tqdm
